pymavlog/__init__.py
pymavlog/core.py
pymavlog/errors.py
pymavlog/helpers.py
pymavlog-0.4.2.dist-info/LICENSE
pymavlog-0.4.2.dist-info/METADATA
pymavlog-0.4.2.dist-info/WHEEL
pymavlog-0.4.2.dist-info/RECORD
