Metadata-Version: 2.1
Name: pymavlog
Version: 0.4.2
Summary: A lightweight python library to parse MavLink log files
Home-page: https://github.com/rmargar/pymavlog
License: MIT
Author: Ricardo Martinez
Author-email: rik@rmargar.net
Requires-Python: >=3.7,<4.0
Classifier: Development Status :: 1 - Planning
Classifier: Intended Audience :: Developers
Classifier: Intended Audience :: Science/Research
Classifier: License :: OSI Approved :: MIT License
Classifier: Operating System :: POSIX
Classifier: Operating System :: Unix
Classifier: Programming Language :: Python :: 3
Classifier: Programming Language :: Python :: 3.7
Classifier: Programming Language :: Python :: 3.8
Classifier: Programming Language :: Python :: 3.9
Classifier: Programming Language :: Python :: 3.10
Classifier: Programming Language :: Python :: 3.11
Classifier: Topic :: Scientific/Engineering :: Mathematics
Classifier: Topic :: Scientific/Engineering :: Physics
Requires-Dist: numpy (>=1.21,<2.0)
Requires-Dist: pymavlink (>=2.4,<3.0)
Project-URL: Repository, https://github.com/rmargar/pymavlog
